LICENSE
README.md
setup.py
spacy_space/__init__.py
spacy_space/engine.py
spacy_space/entities.py
spacy_space/resources.py
spacy_space.egg-info/PKG-INFO
spacy_space.egg-info/SOURCES.txt
spacy_space.egg-info/dependency_links.txt
spacy_space.egg-info/requires.txt
spacy_space.egg-info/top_level.txt
spacy_space/preprocess/__init__.py
spacy_space/preprocess/stringify.py
spacy_space/preprocess/whitespace.py
test/test_available_codes.py
test/test_not_stripped.py